jwt_validator/__init__.py
jwt_validator/exceptions.py
jwt_validator_emagister-2.3.2.dist-info/LICENSE.txt
jwt_validator_emagister-2.3.2.dist-info/METADATA
jwt_validator_emagister-2.3.2.dist-info/WHEEL
jwt_validator_emagister-2.3.2.dist-info/top_level.txt
jwt_validator_emagister-2.3.2.dist-info/RECORD
