Metadata-Version: 2.1
Name: jwt-validator-emagister
Version: 2.3.2
Summary: Access tokens validator. Role checker
Home-page: https://github.com/Emagister/py-jwt-validator.git
Author: Cisco Delgado
Author-email: fdelgado@emagister.com
Requires-Python: >=3.9
License-File: LICENSE.txt
Requires-Dist: PyJWT (==1.5.3)
Requires-Dist: parse (==1.19.0)
Requires-Dist: cryptography (==3.4.7)
